LICENSE.txt
MANIFEST.in
README.md
setup.cfg
setup.py
raas_v2/__init__.py
raas_v2/api_helper.py
raas_v2/configuration.py
raas_v2/decorators.py
raas_v2/raasv2_client.py
raas_v2/controllers/__init__.py
raas_v2/controllers/accounts_controller.py
raas_v2/controllers/base_controller.py
raas_v2/controllers/catalog_controller.py
raas_v2/controllers/customers_controller.py
raas_v2/controllers/exchange_rates_controller.py
raas_v2/controllers/orders_controller.py
raas_v2/controllers/status_controller.py
raas_v2/exceptions/__init__.py
raas_v2/exceptions/api_exception.py
raas_v2/exceptions/raas_4xx_exception.py
raas_v2/exceptions/raas_5xx_exception.py
raas_v2/exceptions/raas_generic_exception.py
raas_v2/http/__init__.py
raas_v2/http/http_call_back.py
raas_v2/http/http_client.py
raas_v2/http/http_context.py
raas_v2/http/http_method_enum.py
raas_v2/http/http_request.py
raas_v2/http/http_response.py
raas_v2/http/requests_client.py
raas_v2/http/auth/__init__.py
raas_v2/http/auth/basic_auth.py
raas_v2/models/__init__.py
raas_v2/models/account_model.py
raas_v2/models/account_summary_model.py
raas_v2/models/brand_model.py
raas_v2/models/catalog_model.py
raas_v2/models/create_account_request_model.py
raas_v2/models/create_customer_request_model.py
raas_v2/models/create_order_request_model.py
raas_v2/models/currency_breakdown_model.py
raas_v2/models/customer_model.py
raas_v2/models/exchange_rate_model.py
raas_v2/models/exchange_rate_response_model.py
raas_v2/models/get_orders_response_model.py
raas_v2/models/item_model.py
raas_v2/models/name_email_model.py
raas_v2/models/order_model.py
raas_v2/models/page_model.py
raas_v2/models/raas_4xx_error_model.py
raas_v2/models/raas_5xx_error_model.py
raas_v2/models/resend_order_response_model.py
raas_v2/models/reward_credential_model.py
raas_v2/models/reward_model.py
raas_v2/models/system_status_response_model.py
tangocard_raasv2.egg-info/PKG-INFO
tangocard_raasv2.egg-info/SOURCES.txt
tangocard_raasv2.egg-info/dependency_links.txt
tangocard_raasv2.egg-info/requires.txt
tangocard_raasv2.egg-info/top_level.txt