Metadata-Version: 1.1
Name: tangocard-raasv2
Version: 1.0.0b2
Summary: With this RESTful API you can integrate a global reward or incentive program into your app or platform. If you have any questions or if you'd like to receive your own credentials, please contact us at devsupport@tangocard.com.
Home-page: https://github.com/tangocard/raas-v2-sdk-python
Author: Tango Card, Inc.
Author-email: devsupport@tangocard.com
License: UNKNOWN
Download-URL: https://github.com/tangocard/raas-v2-sdk-python/archive/1.0.0b2.tar.gz
Platform: UNKNOWN
